{
  "nome": "SegmentoAnf",
  "campos": {
    "00.3Anf": {
      "nome": "controle_banco",
      "posicao_inicio": 1,
      "posicao_fim": 3,
      "formato": "num",
      "default": 341
    },
    "01.3Anf": {
      "nome": "controle_lote",
      "posicao_inicio": 4,
      "posicao_fim": 7,
      "formato": "num",
      "default": 0
    },
    "02.3Anf": {
      "nome": "controle_registro",
      "posicao_inicio": 8,
      "posicao_fim": 8,
      "formato": "num",
      "default": 3
    },
    "03.3Anf": {
      "nome": "servico_numero_registro",
      "posicao_inicio": 9,
      "posicao_fim": 13,
      "formato": "num"
    },
    "04.3Anf": {
      "nome": "servico_segmento",
      "posicao_inicio": 14,
      "posicao_fim": 14,
      "formato": "alfa",
      "default": "A"
    },
    "05.3Anf": {
      "nome": "servico_codigo_movimento",
      "posicao_inicio": 15,
      "posicao_fim": 17,
      "formato": "num"
    },
    "06.3Anf": {
      "nome": "ZEROS",
      "posicao_inicio": 18,
      "posicao_fim": 20,
      "formato": "num",
      "default": 0
    },
    "07.3Anf": {
      "nome": "banco_favorecido",
      "posicao_inicio": 21,
      "posicao_fim": 23,
      "formato": "num"
    },
    "08.3Anf": {
      "nome": "numero_agencia numero_conta",
      "posicao_inicio": 24,
      "posicao_fim": 43,
      "formato": "alfa",
      "default": ""
    },
    "09.3Anf": {
      "nome": "nome_favorecido",
      "posicao_inicio": 44,
      "posicao_fim": 73,
      "formato": "alfa",
      "default": ""
    },
    "10.3Anf": {
      "nome": "seu_numero",
      "posicao_inicio": 74,
      "posicao_fim": 93,
      "formato": "alfa",
      "default": ""
    },
    "11.3Anf": {
      "nome": "data_pagto",
      "posicao_inicio": 94,
      "posicao_fim": 101,
      "formato": "num"
    },
    "12.3Anf": {
      "nome": "tipo_moeda",
      "posicao_inicio": 102,
      "posicao_fim": 104,
      "formato": "alfa",
      "default": ""
    },
    "13.3Anf": {
      "nome": "ZEROS",
      "posicao_inicio": 105,
      "posicao_fim": 119,
      "formato": "num",
      "default": 0
    },
    "14.3Anf": {
      "nome": "valor_pagto",
      "posicao_inicio": 120,
      "posicao_fim": 134,
      "formato": "num"
    },
    "15.3Anf": {
      "nome": "nosso_numero",
      "posicao_inicio": 135,
      "posicao_fim": 149,
      "formato": "alfa",
      "default": ""
    },
    "16.3Anf": {
      "nome": "vazio1",
      "posicao_inicio": 150,
      "posicao_fim": 154,
      "formato": "alfa",
      "default": ""
    },
    "17.3Anf": {
      "nome": "data_efetiva",
      "posicao_inicio": 155,
      "posicao_fim": 162,
      "formato": "num"
    },
    "18.3Anf": {
      "nome": "valor_efetivo",
      "posicao_inicio": 163,
      "posicao_fim": 177,
      "formato": "num"
    },
    "19.3Anf": {
      "nome": "num_nota_fiscal_cnpj",
      "posicao_inicio": 178,
      "posicao_fim": 191,
      "formato": "num"
    },
    "20.3Anf": {
      "nome": "vazio2",
      "posicao_inicio": 192,
      "posicao_fim": 197,
      "formato": "alfa",
      "default": ""
    },
    "21.3Anf": {
      "nome": "numero_documento",
      "posicao_inicio": 198,
      "posicao_fim": 203,
      "formato": "num"
    },
    "22.3Anf": {
      "nome": "numero_inscricao_favorecido",
      "posicao_inicio": 204,
      "posicao_fim": 217,
      "formato": "num"
    },
    "23.3Anf": {
      "nome": "tipo_identificacao",
      "posicao_inicio": 218,
      "posicao_fim": 218,
      "formato": "num"
    },
    "24.3Anf": {
      "nome": "vazio3",
      "posicao_inicio": 219,
      "posicao_fim": 229,
      "formato": "alfa",
      "default": ""
    },
    "25.3Anf": {
      "nome": "aviso_favorecido",
      "posicao_inicio": 230,
      "posicao_fim": 230,
      "formato": "alfa",
      "default": ""
    },
    "26.3Anf": {
      "nome": "ocorencias",
      "posicao_inicio": 231,
      "posicao_fim": 240,
      "formato": "alfa",
      "default": ""
    }
  }
}

